CHANGELOG.md
LICENSE.txt
MANIFEST.in
README.md
requirements.txt
setup.cfg
setup.py
gitsubrepo/__init__.py
gitsubrepo/_common.py
gitsubrepo/_git.py
gitsubrepo/exceptions.py
gitsubrepo/subrepo.py
gitsubrepo.egg-info/PKG-INFO
gitsubrepo.egg-info/SOURCES.txt
gitsubrepo.egg-info/dependency_links.txt
gitsubrepo.egg-info/top_level.txt
gitsubrepo/tests/__init__.py
gitsubrepo/tests/test_subrepo.py
gitsubrepo/tests/_resources/__init__.py
gitsubrepo/tests/_resources/information.py