Metadata-Version: 1.0
Name: gitsubrepo
Version: 1.1.0
Summary: Provides access to `git subrepo` in Python
Home-page: https://github.com/wtsi-hgi/python-git-subrepo
Author: UNKNOWN
Author-email: UNKNOWN
License: MIT
Platform: UNKNOWN
